crafting/__init__.py
crafting/__main__.py
crafting/cli.py
crafting/elements.py
crafting/env.py
crafting/metrics.py
crafting/purpose.py
crafting/requirements.py
crafting/solving_behaviors.py
crafting/state.py
crafting/task.py
crafting/transformation.py
crafting/world.py
crafting/behaviors/__init__.py
crafting/behaviors/actions.py
crafting/behaviors/behaviors.py
crafting/behaviors/feature_conditions.py
crafting/behaviors/utils.py
crafting/examples/__init__.py
crafting/examples/recursive.py
crafting/examples/tower.py
crafting/examples/keydoor/__init__.py
crafting/examples/keydoor/resources/font.ttf
crafting/examples/keydoor/resources/items/ball.png
crafting/examples/keydoor/resources/items/closed_door.png
crafting/examples/keydoor/resources/items/key.png
crafting/examples/keydoor/resources/items/locked_door.png
crafting/examples/keydoor/resources/items/open_door.png
crafting/examples/minecraft/__init__.py
crafting/examples/minecraft/env.py
crafting/examples/minecraft/items.py
crafting/examples/minecraft/tools.py
crafting/examples/minecraft/transformations.py
crafting/examples/minecraft/zones.py
crafting/examples/minecraft/resources/font.ttf
crafting/examples/minecraft/resources/items/blaze_powder.png
crafting/examples/minecraft/resources/items/blaze_rod.png
crafting/examples/minecraft/resources/items/book.png
crafting/examples/minecraft/resources/items/clock.png
crafting/examples/minecraft/resources/items/close_ender_portal.png
crafting/examples/minecraft/resources/items/close_nether_portal.png
crafting/examples/minecraft/resources/items/coal.png
crafting/examples/minecraft/resources/items/cobblestone.png
crafting/examples/minecraft/resources/items/crafting_table.png
crafting/examples/minecraft/resources/items/diamond.png
crafting/examples/minecraft/resources/items/diamond_axe.png
crafting/examples/minecraft/resources/items/diamond_pickaxe.png
crafting/examples/minecraft/resources/items/diamond_shovel.png
crafting/examples/minecraft/resources/items/diamond_sword.png
irll_crafting-1.0.7.dist-info/LICENSE
irll_crafting-1.0.7.dist-info/METADATA
irll_crafting-1.0.7.dist-info/WHEEL
irll_crafting-1.0.7.dist-info/entry_points.txt
irll_crafting-1.0.7.dist-info/top_level.txt
irll_crafting-1.0.7.dist-info/RECORD
